cf_auto_bypass/__init__.py
cf_auto_bypass/bypass.py
cf_auto_bypass-0.1.0.dist-info/licenses/LICENSE
cf_auto_bypass-0.1.0.dist-info/METADATA
cf_auto_bypass-0.1.0.dist-info/WHEEL
cf_auto_bypass-0.1.0.dist-info/top_level.txt
cf_auto_bypass-0.1.0.dist-info/RECORD
